fastweixin/__init__.py
fastweixin/fastweixin.py
fastweixin-0.0.9.dist-info/licenses/LICENSE
fastweixin-0.0.9.dist-info/METADATA
fastweixin-0.0.9.dist-info/WHEEL
fastweixin-0.0.9.dist-info/top_level.txt
fastweixin-0.0.9.dist-info/RECORD
