Metadata-Version: 2.4
Name: fastweixin
Version: 0.0.9
Summary: make it easy to use weixin
Home-page: https://gitee.com/ZeroSeeker/fastweixin
Author: ZeroSeeker
Author-email: zeroseeker@foxmail.com
Classifier: Programming Language :: Python :: 3
Classifier: License :: OSI Approved :: MIT License
Classifier: Operating System :: OS Independent
License-File: LICENSE
Requires-Dist: lxml==4.9.0
Requires-Dist: lazysdk==0.1.110
Dynamic: author
Dynamic: author-email
Dynamic: classifier
Dynamic: home-page
Dynamic: license-file
Dynamic: requires-dist
Dynamic: summary
